ponio/__init__.py
ponio/__main__.py
ponio/runge_kutta.py
ponio/utils.py
ponio/von_neumann.py
ponio/weno.py
ponio/template/rk.temp.cc
ponio/template/rk.temp.json
ponio-0.1.dist-info/LICENSE
ponio-0.1.dist-info/METADATA
ponio-0.1.dist-info/WHEEL
ponio-0.1.dist-info/top_level.txt
ponio-0.1.dist-info/RECORD
