Metadata-Version: 2.1
Name: ponio
Version: 0.1
Summary: Python Objects for Numerical IntegratOr
Home-page: http://github.com/kivvix/miMas/ponio
Author: Josselin Massot
Author-email: josselin.massot@univ-rennes1.fr
License: WTFPL
Platform: UNKNOWN
Classifier: Programming Language :: Python
Classifier: Development Status :: 1 - Planning
Classifier: License :: OSI Approved
Classifier: Natural Language :: French
Classifier: Operating System :: OS Independent
Classifier: Programming Language :: Python :: 3
Classifier: Topic :: Scientific/Engineering :: Mathematics
Requires-Dist: matplotlib
Requires-Dist: numpy
Requires-Dist: sympy
Requires-Dist: jinja2
